mrh/__init__.py
mrh/mrh.py
mrh-0.0.3.dist-info/LICENSE
mrh-0.0.3.dist-info/METADATA
mrh-0.0.3.dist-info/WHEEL
mrh-0.0.3.dist-info/top_level.txt
mrh-0.0.3.dist-info/RECORD
